math_python/__init__.py
math_python/math_python.py
math_python-0.0.2.5.dist-info/LICENSE
math_python-0.0.2.5.dist-info/METADATA
math_python-0.0.2.5.dist-info/WHEEL
math_python-0.0.2.5.dist-info/top_level.txt
math_python-0.0.2.5.dist-info/RECORD
