Metadata-Version: 2.1
Name: math-python
Version: 0.0.2.5
Summary: Gaussian and Binomial distributions
Home-page: UNKNOWN
Author: UNKNOWN
Author-email: vertikal2312312@yandex.ru
License: UNKNOWN
Platform: UNKNOWN
